neuralintents/__init__.py
neuralintents/main.py
xneuralintents-0.0.6.dist-info/LICENSE
xneuralintents-0.0.6.dist-info/METADATA
xneuralintents-0.0.6.dist-info/WHEEL
xneuralintents-0.0.6.dist-info/top_level.txt
xneuralintents-0.0.6.dist-info/RECORD
