Metadata-Version: 2.1
Name: xneuralintents
Version: 0.0.6
Summary: Simple interface for working with intents and chatbots.
Author: NeuralNine (Florian Dedov)
Author-email: <mail@neuralnine.com>
Keywords: python,neural,machine learning,chatbots,chat,artificial intelligence,virtual assistant
Classifier: Development Status :: 1 - Planning
Classifier: Intended Audience :: Developers
Classifier: Programming Language :: Python :: 3
Classifier: Operating System :: Unix
Classifier: Operating System :: Microsoft :: Windows
License-File: LICENSE
Requires-Dist: numpy
Requires-Dist: nltk
Requires-Dist: tensorflow
